MANIFEST.in
README.md
ez_setup.py
setup.py
Metaphor.egg-info/PKG-INFO
Metaphor.egg-info/SOURCES.txt
Metaphor.egg-info/dependency_links.txt
Metaphor.egg-info/not-zip-safe
Metaphor.egg-info/requires.txt
Metaphor.egg-info/top_level.txt
metaphor/__init__.py
metaphor/cythonlist.txt
metaphor/services_pp.txt
metaphor/version.py
metaphor.egg-info/PKG-INFO
metaphor.egg-info/SOURCES.txt
metaphor.egg-info/dependency_links.txt
metaphor.egg-info/entry_points.txt
metaphor.egg-info/not-zip-safe
metaphor.egg-info/requires.txt
metaphor.egg-info/top_level.txt
metaphor/monal/Property.c
metaphor/monal/__init__.py
metaphor/monal/modelutils.c
metaphor/monal/monalconst.py
metaphor/monal/monalrecords.py
metaphor/monal/specialmath.py
metaphor/monal/test.py
metaphor/monal/version.py
metaphor/monal/driver/__init__.py
metaphor/monal/driver/_driver.c
metaphor/monal/driver/_driverlib.py
metaphor/monal/driver/_drivermultidyn.py
metaphor/monal/driver/_networkfactory.py
metaphor/monal/driver/_optimizer.c
metaphor/monal/driver/_parallelJobs.py
metaphor/monal/driver/_workshop.c
metaphor/monal/include/mathplus.h
metaphor/monal/include/ntdefines.h
metaphor/monal/include/nttoolbox.h
metaphor/monal/include/nttype.h
metaphor/monal/include/train.h
metaphor/monal/lcode/__init__.py
metaphor/monal/lcode/ccrypt.c
metaphor/monal/lcode/codeconst.c
metaphor/monal/lcode/codewriter.c
metaphor/monal/lcode/codewriterC.c
metaphor/monal/lcode/codewriterdetailC.c
metaphor/monal/lcode/code_templates/Base.cc
metaphor/monal/lcode/code_templates/Base.h
metaphor/monal/lcode/code_templates/BaseEx.cc
metaphor/monal/lcode/code_templates/BaseEx.h
metaphor/monal/lcode/code_templates/deploy.txt
metaphor/monal/lcode/code_templates/interfaceC.cc
metaphor/monal/lcode/code_templates/interfacetraindll.cc
metaphor/monal/lcode/code_templates/interfacetraindll.h
metaphor/monal/lcode/code_templates/interfaceusedll.cc
metaphor/monal/lcode/code_templates/interfaceusedll.h
metaphor/monal/lcode/code_templates/jurfr.txt
metaphor/monal/lcode/code_templates/jurgb.txt
metaphor/monal/lcode/code_templates/licfr.txt
metaphor/monal/lcode/code_templates/licgb.txt
metaphor/monal/lcode/code_templates/trainbase.cc
metaphor/monal/lcode/code_templates/trainbase.h
metaphor/monal/lcode/code_templates/usebase.cc
metaphor/monal/lcode/code_templates/usebase.h
metaphor/monal/lcode/code_templates/common/mathplus.cc
metaphor/monal/lcode/code_templates/common/nttoolbox.cc
